{
    "location_BlogUrls": {
        "Kadra": [
            "http://travel.paintedstork.com/blog/2005/08/drive-in-rains-jog-falls-karwar-kali.html"
        ],
        "Geruoppe Falls": [
            "http://travel.india.com/jog-falls/"
        ],
        "Goa Goa": [
            "https://www.quora.com/What-are-the-best-places-to-visit-in-between-Mangalore-to-Goa-on-a-road-trip"
        ],
        "Dharwad": [
            "https://besttimetovisitjogfalls.wordpress.com/tag/karnataka-tourism/",
            "https://besttimetovisitjogfalls.wordpress.com/tag/falls-in-karnataka/"
        ],
        "Western Ghats": [
            "http://www.nivalink.com/destination/jog-falls"
        ],
        "Coastal Karnataka": [
            "http://www.nivalink.com/destination/jog-falls"
        ],
        "Kalinadi": [
            "http://travel.paintedstork.com/blog/2005/08/drive-in-rains-jog-falls-karwar-kali.html"
        ],
        "Gersoppa Falls": [
            "http://travel.india.com/jog-falls/"
        ],
        "Nohkalikai Falls": [
            "http://travel.india.com/jog-falls/places-to-visit/",
            "http://www.nivalink.com/destination/jog-falls"
        ],
        "Ikkeri": [
            "http://www.nivalink.com/destination/jog-falls"
        ],
        "Sharavathi": [
            "http://blog.sterlingholidays.com/jog-falls-karnataka-one-of-the-highest-falls-in-asia/"
        ],
        "Sagara": [
            "http://travel.india.com/jog-falls/places-to-visit/",
            "http://www.indiamike.com/india/karnataka-f38/help-required-on-weekend-tour-to-jog-falls-t141156/",
            "http://www.nivalink.com/destination/jog-falls"
        ],
        "Vijayanagara": [
            "http://www.nivalink.com/destination/jog-falls"
        ],
        "Dakshina Kannada District": [
            "https://besttimetovisitjogfalls.wordpress.com/tag/karnataka-tourism/",
            "https://besttimetovisitjogfalls.wordpress.com/tag/falls-in-karnataka/"
        ],
        "Unchalli Falls": [
            "https://www.quora.com/What-are-the-best-places-to-visit-in-between-Mangalore-to-Goa-on-a-road-trip"
        ],
        "Shantadurga": [
            "http://www.indianholiday.com/tours-of-india/jog-falls-trip-bangalore.html"
        ],
        "Mandovi": [
            "http://www.indianholiday.com/tours-of-india/jog-falls-trip-bangalore.html"
        ],
        "Alekan Waterfalls": [
            "https://besttimetovisitjogfalls.wordpress.com/tag/karnataka-tourism/",
            "https://besttimetovisitjogfalls.wordpress.com/tag/falls-in-karnataka/"
        ],
        "Greenseer": [
            "http://www.karnatakatourism.org/"
        ],
        "Sri Karinjeshwara": [
            "http://www.indiamike.com/india/karnataka-f38/udupi-agumbe-shringeri-murudeshwara-jog-falls-dharmasthala-t137208/"
        ],
        "Asia": [
            "http://www.nivalink.com/destination/jog-falls"
        ],
        "Karwar": [
            "https://www.quora.com/What-are-the-best-places-to-visit-in-between-Mangalore-to-Goa-on-a-road-trip",
            "http://travel.paintedstork.com/blog/2005/08/drive-in-rains-jog-falls-karwar-kali.html"
        ],
        "Maharashtra": [
            "https://www.tripoto.com/trip/bangalore-to-jog-falls-karnataka"
        ],
        "Dakshina Kedara": [
            "http://www.nivalink.com/destination/jog-falls"
        ],
        "Arabian Sea": [
            "http://blog.sterlingholidays.com/jog-falls-karnataka-one-of-the-highest-falls-in-asia/"
        ],
        "Niagara": [
            "https://besttimetovisitjogfalls.wordpress.com/tag/karnataka-tourism/",
            "http://travel.paintedstork.com/blog/2005/08/drive-in-rains-jog-falls-karwar-kali.html"
        ],
        "Jog Falls": [
            "https://www.tripadvisor.in/Attraction_Review-g1156205-d1206548-Reviews-Jog_Falls-Shimoga_Karnataka.html",
            "http://travel.india.com/jog-falls/places-to-visit/",
            "http://travel.india.com/jog-falls/"
        ],
        "Panaj": [
            "http://www.indianholiday.com/tours-of-india/jog-falls-trip-bangalore.html"
        ],
        "South India": [
            "https://besttimetovisitjogfalls.wordpress.com/tag/karnataka-tourism/"
        ],
        "Ambutheertha": [
            "http://blog.sterlingholidays.com/jog-falls-karnataka-one-of-the-highest-falls-in-asia/"
        ],
        "Kundapur": [
            "https://www.quora.com/What-are-the-best-places-to-visit-in-between-Mangalore-to-Goa-on-a-road-trip"
        ],
        "Andhra Pradesh": [
            "https://www.tripoto.com/trip/bangalore-to-jog-falls-karnataka"
        ],
        "Panaji": [
            "http://www.indianholiday.com/tours-of-india/jog-falls-trip-bangalore.html"
        ],
        "Dadu": [
            "http://travel.paintedstork.com/blog/2005/08/drive-in-rains-jog-falls-karwar-kali.html"
        ],
        "South India.Udupi - World 's Famous Krishna Temple": [
            "https://www.quora.com/What-are-the-best-places-to-visit-in-between-Mangalore-to-Goa-on-a-road-trip"
        ],
        "Mangeshi": [
            "http://www.indianholiday.com/tours-of-india/jog-falls-trip-bangalore.html"
        ],
        "Kundapura": [
            "http://www.nivalink.com/destination/jog-falls"
        ],
        "Sharavati": [
            "http://travel.paintedstork.com/blog/2005/08/drive-in-rains-jog-falls-karwar-kali.html",
            "http://www.bangaloretrips.info/jogfalls"
        ],
        "Vagator": [
            "http://www.indianholiday.com/tours-of-india/jog-falls-trip-bangalore.html"
        ],
        "BalligaviKedaresvara Temple": [
            "http://www.nivalink.com/destination/jog-falls"
        ],
        "Chimkmagalur": [
            "http://www.nivalink.com/destination/jog-falls"
        ],
        "Russia": [
            "https://www.tripoto.com/trip/bangalore-to-jog-falls-karnataka"
        ],
        "Kemmannugundi": [
            "http://www.nivalink.com/destination/jog-falls"
        ],
        "Pakistan": [
            "https://www.quora.com/What-are-the-best-places-to-visit-in-between-Mangalore-to-Goa-on-a-road-trip"
        ],
        "Murdeshwara": [
            "http://www.indiamike.com/india/karnataka-f38/udupi-agumbe-shringeri-murudeshwara-jog-falls-dharmasthala-t137208/"
        ],
        "Sagar": [
            "http://blog.sterlingholidays.com/jog-falls-karnataka-one-of-the-highest-falls-in-asia/",
            "http://travel.paintedstork.com/blog/2005/08/drive-in-rains-jog-falls-karwar-kali.html"
        ],
        "Magod Falls": [
            "https://www.quora.com/What-are-the-best-places-to-visit-in-between-Mangalore-to-Goa-on-a-road-trip"
        ],
        "Tumkur": [
            "http://travel.paintedstork.com/blog/2005/08/drive-in-rains-jog-falls-karwar-kali.html"
        ],
        "Shikra": [
            "https://www.tripadvisor.in/Attraction_Review-g1156205-d1206548-Reviews-Jog_Falls-Shimoga_Karnataka.html"
        ],
        "Shimoga": [
            "https://besttimetovisitjogfalls.wordpress.com/tag/karnataka-tourism/",
            "https://besttimetovisitjogfalls.wordpress.com/tag/falls-in-karnataka/"
        ],
        "Portland": [
            "https://www.quora.com/What-are-the-best-places-to-visit-in-between-Mangalore-to-Goa-on-a-road-trip"
        ],
        "Tunga River": [
            "http://travel.india.com/jog-falls/places-to-visit/"
        ],
        "Agumbe": [
            "https://besttimetovisitjogfalls.wordpress.com/tag/karnataka-tourism/",
            "https://besttimetovisitjogfalls.wordpress.com/tag/falls-in-karnataka/"
        ],
        "Kalaseshwara Temple": [
            "https://besttimetovisitjogfalls.wordpress.com/tag/falls-in-karnataka/"
        ],
        "Karnataka": [
            "http://travel.india.com/jog-falls/places-to-visit/",
            "http://travel.india.com/jog-falls/",
            "http://www.nivalink.com/destination/jog-falls",
            "https://www.quora.com/What-are-the-best-places-to-visit-in-between-Mangalore-to-Goa-on-a-road-trip",
            "https://www.tripoto.com/trip/bangalore-to-jog-falls-karnataka",
            "http://travel.paintedstork.com/blog/2005/08/drive-in-rains-jog-falls-karwar-kali.html",
            "https://besttimetovisitjogfalls.wordpress.com/tag/karnataka-tourism/",
            "http://blog.sterlingholidays.com/jog-falls-karnataka-one-of-the-highest-falls-in-asia/",
            "http://www.indianholiday.com/tours-of-india/jog-falls-trip-bangalore.html",
            "https://besttimetovisitjogfalls.wordpress.com/tag/falls-in-karnataka/",
            "http://www.karnatakatourism.org/"
        ],
        "Nandi Hills": [
            "https://besttimetovisitjogfalls.wordpress.com/tag/karnataka-tourism/"
        ],
        "Kemmannugundi Hill": [
            "https://besttimetovisitjogfalls.wordpress.com/tag/karnataka-tourism/"
        ],
        "Mayura Gerusoppa": [
            "https://www.tripadvisor.in/Attraction_Review-g1156205-d1206548-Reviews-Jog_Falls-Shimoga_Karnataka.html"
        ],
        "Horanadu": [
            "http://www.indiamike.com/india/karnataka-f38/udupi-agumbe-shringeri-murudeshwara-jog-falls-dharmasthala-t137208/"
        ],
        "Bhatkal": [
            "https://www.tripadvisor.in/Attraction_Review-g1156205-d1206548-Reviews-Jog_Falls-Shimoga_Karnataka.html"
        ],
        "Lingamakki": [
            "http://www.bangaloretrips.info/jogfalls"
        ],
        "Calangute Beach": [
            "http://www.indianholiday.com/tours-of-india/jog-falls-trip-bangalore.html"
        ],
        "Kemmangundi": [
            "https://besttimetovisitjogfalls.wordpress.com/tag/karnataka-tourism/",
            "https://besttimetovisitjogfalls.wordpress.com/tag/falls-in-karnataka/"
        ],
        "Udipi": [
            "http://www.nivalink.com/destination/jog-falls"
        ],
        "Karawar": [
            "http://travel.paintedstork.com/blog/2005/08/drive-in-rains-jog-falls-karwar-kali.html"
        ],
        "Bogmalo": [
            "https://www.quora.com/What-are-the-best-places-to-visit-in-between-Mangalore-to-Goa-on-a-road-trip"
        ],
        "Tagore": [
            "https://www.quora.com/What-are-the-best-places-to-visit-in-between-Mangalore-to-Goa-on-a-road-trip"
        ],
        "Sharavathi River": [
            "http://travel.india.com/jog-falls/places-to-visit/",
            "http://travel.india.com/jog-falls/",
            "http://www.nivalink.com/destination/jog-falls"
        ],
        "Britain": [
            "https://www.quora.com/What-are-the-best-places-to-visit-in-between-Mangalore-to-Goa-on-a-road-trip"
        ],
        "Linganamakki": [
            "http://travel.india.com/jog-falls/places-to-visit/",
            "http://blog.sterlingholidays.com/jog-falls-karnataka-one-of-the-highest-falls-in-asia/"
        ],
        "Thirthahalli Taluk of Shimoga": [
            "http://blog.sterlingholidays.com/jog-falls-karnataka-one-of-the-highest-falls-in-asia/"
        ],
        "South": [
            "http://www.nivalink.com/destination/jog-falls"
        ],
        "Dabbe Falls": [
            "http://travel.india.com/jog-falls/places-to-visit/"
        ],
        "Dakshina Kannada District of Karnataka": [
            "https://besttimetovisitjogfalls.wordpress.com/tag/karnataka-tourism/",
            "https://besttimetovisitjogfalls.wordpress.com/tag/falls-in-karnataka/"
        ],
        "Goa": [
            "http://www.team-bhp.com/forum/route-travel-queries/29629-bangalore-shimogga-jog-falls-goa-mangalore-bangalore-route.html",
            "http://www.indianholiday.com/tours-of-india/jog-falls-trip-bangalore.html",
            "https://www.quora.com/What-are-the-best-places-to-visit-in-between-Mangalore-to-Goa-on-a-road-trip",
            "http://travel.paintedstork.com/blog/2005/08/drive-in-rains-jog-falls-karwar-kali.html"
        ],
        "Sathodi Falls": [
            "https://www.quora.com/What-are-the-best-places-to-visit-in-between-Mangalore-to-Goa-on-a-road-trip"
        ],
        "Mangalore": [
            "http://www.team-bhp.com/forum/route-travel-queries/29629-bangalore-shimogga-jog-falls-goa-mangalore-bangalore-route.html",
            "https://besttimetovisitjogfalls.wordpress.com/tag/karnataka-tourism/",
            "https://www.tripoto.com/trip/bangalore-to-jog-falls-karnataka",
            "https://www.quora.com/What-are-the-best-places-to-visit-in-between-Mangalore-to-Goa-on-a-road-trip",
            "http://travel.paintedstork.com/blog/2005/08/drive-in-rains-jog-falls-karwar-kali.html"
        ],
        "Varada": [
            "http://www.nivalink.com/destination/jog-falls"
        ],
        "Hyderabad": [
            "https://www.quora.com/What-are-the-best-places-to-visit-in-between-Mangalore-to-Goa-on-a-road-trip"
        ],
        "Gokarna Beach": [
            "https://www.tripadvisor.in/Attraction_Review-g1156205-d1206548-Reviews-Jog_Falls-Shimoga_Karnataka.html"
        ],
        "North Kanara": [
            "http://www.indiamike.com/india/karnataka-f38/help-required-on-weekend-tour-to-jog-falls-t141156/",
            "https://www.quora.com/What-are-the-best-places-to-visit-in-between-Mangalore-to-Goa-on-a-road-trip"
        ],
        "Kalasa": [
            "http://www.team-bhp.com/forum/route-travel-queries/29629-bangalore-shimogga-jog-falls-goa-mangalore-bangalore-route.html"
        ],
        "UK": [
            "https://www.quora.com/What-are-the-best-places-to-visit-in-between-Mangalore-to-Goa-on-a-road-trip"
        ],
        "Half Moon or Paradise Beach": [
            "https://www.quora.com/What-are-the-best-places-to-visit-in-between-Mangalore-to-Goa-on-a-road-trip"
        ],
        "Seattle": [
            "https://www.quora.com/What-are-the-best-places-to-visit-in-between-Mangalore-to-Goa-on-a-road-trip"
        ],
        "Swa Swara": [
            "http://www.indiamike.com/india/karnataka-f38/udupi-agumbe-shringeri-murudeshwara-jog-falls-dharmasthala-t137208/"
        ],
        "Hubli": [
            "https://besttimetovisitjogfalls.wordpress.com/tag/karnataka-tourism/",
            "http://www.nivalink.com/destination/jog-falls",
            "https://besttimetovisitjogfalls.wordpress.com/tag/falls-in-karnataka/",
            "https://www.tripoto.com/trip/bangalore-to-jog-falls-karnataka"
        ],
        "Ankola": [
            "http://www.indianholiday.com/tours-of-india/jog-falls-trip-bangalore.html",
            "https://besttimetovisitjogfalls.wordpress.com/tag/karnataka-tourism/",
            "https://besttimetovisitjogfalls.wordpress.com/tag/falls-in-karnataka/",
            "http://blog.sterlingholidays.com/jog-falls-karnataka-one-of-the-highest-falls-in-asia/"
        ],
        "Hoysala": [
            "http://www.nivalink.com/destination/jog-falls"
        ],
        "Hebbe Falls": [
            "https://besttimetovisitjogfalls.wordpress.com/tag/karnataka-tourism/",
            "https://besttimetovisitjogfalls.wordpress.com/tag/falls-in-karnataka/"
        ],
        "Veluji": [
            "http://www.indiamike.com/india/karnataka-f38/udupi-agumbe-shringeri-murudeshwara-jog-falls-dharmasthala-t137208/"
        ],
        "Croatia": [
            "http://travel.india.com/jog-falls/places-to-visit/",
            "http://travel.india.com/jog-falls/",
            "http://www.nivalink.com/destination/jog-falls",
            "http://www.bangaloretrips.info/jogfalls"
        ],
        "Keladi": [
            "http://www.nivalink.com/destination/jog-falls"
        ],
        "India": [
            "http://travel.india.com/jog-falls/places-to-visit/",
            "http://travel.india.com/jog-falls/",
            "http://www.nivalink.com/destination/jog-falls",
            "https://www.quora.com/What-are-the-best-places-to-visit-in-between-Mangalore-to-Goa-on-a-road-trip",
            "https://www.tripoto.com/trip/bangalore-to-jog-falls-karnataka",
            "http://travel.paintedstork.com/blog/2005/08/drive-in-rains-jog-falls-karwar-kali.html",
            "http://www.indiamike.com/india/karnataka-f38/help-required-on-weekend-tour-to-jog-falls-t141156/",
            "http://www.team-bhp.com/forum/route-travel-queries/29629-bangalore-shimogga-jog-falls-goa-mangalore-bangalore-route.html",
            "https://besttimetovisitjogfalls.wordpress.com/tag/karnataka-tourism/",
            "http://blog.sterlingholidays.com/jog-falls-karnataka-one-of-the-highest-falls-in-asia/",
            "http://www.indianholiday.com/tours-of-india/jog-falls-trip-bangalore.html",
            "https://besttimetovisitjogfalls.wordpress.com/tag/falls-in-karnataka/",
            "http://www.bangaloretrips.info/jogfalls"
        ],
        "Calangunte": [
            "https://www.quora.com/What-are-the-best-places-to-visit-in-between-Mangalore-to-Goa-on-a-road-trip"
        ],
        "Sahasralinga": [
            "https://www.quora.com/What-are-the-best-places-to-visit-in-between-Mangalore-to-Goa-on-a-road-trip"
        ],
        "Swarna Nadi": [
            "http://travel.india.com/jog-falls/"
        ],
        "Sahyadri Mountains": [
            "https://besttimetovisitjogfalls.wordpress.com/tag/karnataka-tourism/",
            "https://besttimetovisitjogfalls.wordpress.com/tag/falls-in-karnataka/"
        ],
        "KSTDC Maurya Hotel": [
            "http://travel.india.com/jog-falls/"
        ],
        "Meghalaya": [
            "http://travel.india.com/jog-falls/places-to-visit/",
            "http://travel.india.com/jog-falls/",
            "http://www.nivalink.com/destination/jog-falls"
        ],
        "Sharavati Valley": [
            "http://travel.paintedstork.com/blog/2005/08/drive-in-rains-jog-falls-karwar-kali.html"
        ],
        "Honnavar": [
            "http://blog.sterlingholidays.com/jog-falls-karnataka-one-of-the-highest-falls-in-asia/"
        ],
        "Aguada Beach": [
            "http://www.indianholiday.com/tours-of-india/jog-falls-trip-bangalore.html"
        ],
        "Hosagadde": [
            "http://travel.india.com/jog-falls/places-to-visit/"
        ],
        "Sadashivgad Fort": [
            "https://www.quora.com/What-are-the-best-places-to-visit-in-between-Mangalore-to-Goa-on-a-road-trip"
        ],
        "Garden City": [
            "http://www.indianholiday.com/tours-of-india/jog-falls-trip-bangalore.html"
        ],
        "Devbagh Island - Island": [
            "https://www.quora.com/What-are-the-best-places-to-visit-in-between-Mangalore-to-Goa-on-a-road-trip"
        ],
        "india": [
            "https://besttimetovisitjogfalls.wordpress.com/tag/karnataka-tourism/"
        ],
        "Niagara Falls": [
            "http://travel.paintedstork.com/blog/2005/08/drive-in-rains-jog-falls-karwar-kali.html"
        ],
        "USA": [
            "https://www.quora.com/What-are-the-best-places-to-visit-in-between-Mangalore-to-Goa-on-a-road-trip"
        ],
        "Kolhapur": [
            "https://www.tripoto.com/trip/bangalore-to-jog-falls-karnataka"
        ],
        "Charmadi": [
            "https://besttimetovisitjogfalls.wordpress.com/tag/karnataka-tourism/",
            "https://besttimetovisitjogfalls.wordpress.com/tag/falls-in-karnataka/"
        ],
        "Gokarna": [
            "http://www.indiamike.com/india/karnataka-f38/udupi-agumbe-shringeri-murudeshwara-jog-falls-dharmasthala-t137208/",
            "http://www.indianholiday.com/tours-of-india/jog-falls-trip-bangalore.html",
            "http://www.indiamike.com/india/karnataka-f38/help-required-on-weekend-tour-to-jog-falls-t141156/"
        ],
        "Bombay Bungalow": [
            "http://travel.india.com/jog-falls/"
        ],
        "Kali": [
            "http://travel.paintedstork.com/blog/2005/08/drive-in-rains-jog-falls-karwar-kali.html"
        ],
        "Bangalore": [
            "http://travel.india.com/jog-falls/",
            "http://www.nivalink.com/destination/jog-falls",
            "https://www.quora.com/What-are-the-best-places-to-visit-in-between-Mangalore-to-Goa-on-a-road-trip",
            "https://www.tripoto.com/trip/bangalore-to-jog-falls-karnataka",
            "http://travel.paintedstork.com/blog/2005/08/drive-in-rains-jog-falls-karwar-kali.html",
            "http://www.team-bhp.com/forum/route-travel-queries/29629-bangalore-shimogga-jog-falls-goa-mangalore-bangalore-route.html",
            "https://besttimetovisitjogfalls.wordpress.com/tag/karnataka-tourism/",
            "http://blog.sterlingholidays.com/jog-falls-karnataka-one-of-the-highest-falls-in-asia/",
            "https://www.tripadvisor.in/Attraction_Review-g1156205-d1206548-Reviews-Jog_Falls-Shimoga_Karnataka.html",
            "http://www.indianholiday.com/tours-of-india/jog-falls-trip-bangalore.html",
            "https://besttimetovisitjogfalls.wordpress.com/tag/falls-in-karnataka/"
        ],
        "Tunga Anicut Dam": [
            "http://travel.india.com/jog-falls/places-to-visit/"
        ],
        "Palolem": [
            "http://travel.paintedstork.com/blog/2005/08/drive-in-rains-jog-falls-karwar-kali.html"
        ],
        "Kempegowda Airport Bangalore": [
            "https://www.tripoto.com/trip/bangalore-to-jog-falls-karnataka"
        ],
        "Gangavathi": [
            "http://www.nivalink.com/destination/jog-falls"
        ],
        "Anjuna Beach": [
            "http://www.indianholiday.com/tours-of-india/jog-falls-trip-bangalore.html"
        ],
        "Sita River": [
            "https://besttimetovisitjogfalls.wordpress.com/tag/karnataka-tourism/",
            "https://besttimetovisitjogfalls.wordpress.com/tag/falls-in-karnataka/"
        ],
        "Himalayas": [
            "http://travel.paintedstork.com/blog/2005/08/drive-in-rains-jog-falls-karwar-kali.html"
        ],
        "Marikamba": [
            "http://www.indiamike.com/india/karnataka-f38/help-required-on-weekend-tour-to-jog-falls-t141156/"
        ],
        "Chitradurga": [
            "http://www.team-bhp.com/forum/route-travel-queries/29629-bangalore-shimogga-jog-falls-goa-mangalore-bangalore-route.html"
        ],
        "Maurya": [
            "http://travel.india.com/jog-falls/"
        ],
        "Ponda": [
            "http://www.indianholiday.com/tours-of-india/jog-falls-trip-bangalore.html"
        ],
        "Ooty": [
            "https://besttimetovisitjogfalls.wordpress.com/tag/karnataka-tourism/"
        ],
        "B.R Hills Wildlife Sanctuary": [
            "https://besttimetovisitjogfalls.wordpress.com/tag/karnataka-tourism/"
        ],
        "Pune": [
            "http://www.indiamike.com/india/karnataka-f38/udupi-agumbe-shringeri-murudeshwara-jog-falls-dharmasthala-t137208/"
        ],
        "Keledi": [
            "http://www.indiamike.com/india/karnataka-f38/help-required-on-weekend-tour-to-jog-falls-t141156/"
        ],
        "Florence": [
            "https://www.quora.com/What-are-the-best-places-to-visit-in-between-Mangalore-to-Goa-on-a-road-trip"
        ],
        "Balligavi": [
            "http://www.nivalink.com/destination/jog-falls"
        ],
        "Linganamakki Dam": [
            "http://travel.india.com/jog-falls/"
        ],
        "Kapu": [
            "https://www.tripoto.com/trip/bangalore-to-jog-falls-karnataka"
        ],
        "Uttara Kannada": [
            "http://blog.sterlingholidays.com/jog-falls-karnataka-one-of-the-highest-falls-in-asia/"
        ],
        "Bakhim": [
            "http://travel.paintedstork.com/blog/2005/08/drive-in-rains-jog-falls-karwar-kali.html"
        ],
        "Mumbai": [
            "https://www.tripoto.com/trip/bangalore-to-jog-falls-karnataka"
        ],
        "Shringeri": [
            "http://www.indiamike.com/india/karnataka-f38/udupi-agumbe-shringeri-murudeshwara-jog-falls-dharmasthala-t137208/"
        ],
        "KeladiRameshwara Temple": [
            "http://www.nivalink.com/destination/jog-falls"
        ],
        "Sharavati River": [
            "http://travel.india.com/jog-falls/"
        ]
    },
    "blogUrl_Locations": {
        "http://www.indiamike.com/india/karnataka-f38/udupi-agumbe-shringeri-murudeshwara-jog-falls-dharmasthala-t137208/": [
            "Swa Swara",
            "Pune",
            "Gokarna",
            "Veluji",
            "Shringeri",
            "Horanadu",
            "Murdeshwara",
            "Sri Karinjeshwara"
        ],
        "http://www.indiamike.com/india/karnataka-f38/help-required-on-weekend-tour-to-jog-falls-t141156/": [
            "Keledi",
            "Gokarna",
            "Sagara",
            "India",
            "Marikamba",
            "North Kanara"
        ],
        "https://besttimetovisitjogfalls.wordpress.com/tag/karnataka-tourism/": [
            "Kemmangundi",
            "Dharwad",
            "Dakshina Kannada District of Karnataka",
            "Dakshina Kannada District",
            "Mangalore",
            "Alekan Waterfalls",
            "Niagara",
            "Hubli",
            "Ankola",
            "Hebbe Falls",
            "India",
            "South India",
            "india",
            "Charmadi",
            "Bangalore",
            "Sita River",
            "Ooty",
            "B.R Hills Wildlife Sanctuary",
            "Shimoga",
            "Agumbe",
            "Nandi Hills",
            "Karnataka",
            "Kemmannugundi Hill",
            "Sahyadri Mountains"
        ],
        "http://travel.india.com/jog-falls/places-to-visit/": [
            "Tunga Anicut Dam",
            "Tunga River",
            "Jog Falls",
            "Sharavathi River",
            "Nohkalikai Falls",
            "Linganamakki",
            "Croatia",
            "Sagara",
            "India",
            "Dabbe Falls",
            "Hosagadde",
            "Karnataka",
            "Meghalaya"
        ],
        "http://travel.india.com/jog-falls/": [
            "Geruoppe Falls",
            "KSTDC Maurya Hotel",
            "Jog Falls",
            "Sharavathi River",
            "Gersoppa Falls",
            "Bangalore",
            "Bombay Bungalow",
            "Croatia",
            "Linganamakki Dam",
            "India",
            "Karnataka",
            "Swarna Nadi",
            "Meghalaya",
            "Sharavati River",
            "Maurya"
        ],
        "http://www.nivalink.com/destination/jog-falls": [
            "Ikkeri",
            "Udipi",
            "Western Ghats",
            "Sharavathi River",
            "Nohkalikai Falls",
            "Sagara",
            "South",
            "Vijayanagara",
            "Varada",
            "Asia",
            "KeladiRameshwara Temple",
            "Dakshina Kedara",
            "Hubli",
            "Hoysala",
            "Croatia",
            "India",
            "Coastal Karnataka",
            "Balligavi",
            "Meghalaya",
            "Kundapura",
            "Bangalore",
            "Keladi",
            "BalligaviKedaresvara Temple",
            "Chimkmagalur",
            "Gangavathi",
            "Kemmannugundi",
            "Karnataka"
        ],
        "https://www.quora.com/What-are-the-best-places-to-visit-in-between-Mangalore-to-Goa-on-a-road-trip": [
            "Bogmalo",
            "Tagore",
            "Britain",
            "Goa",
            "Sathodi Falls",
            "Mangalore",
            "Hyderabad",
            "North Kanara",
            "UK",
            "Half Moon or Paradise Beach",
            "Karwar",
            "Seattle",
            "Goa Goa",
            "Unchalli Falls",
            "India",
            "Calangunte",
            "Sahasralinga",
            "Portland",
            "Kundapur",
            "South India.Udupi - World 's Famous Krishna Temple",
            "USA",
            "Devbagh Island - Island",
            "Bangalore",
            "Pakistan",
            "Sadashivgad Fort",
            "Magod Falls",
            "Florence",
            "Karnataka"
        ],
        "https://besttimetovisitjogfalls.wordpress.com/tag/falls-in-karnataka/": [
            "Kemmangundi",
            "Dharwad",
            "Shimoga",
            "Charmadi",
            "Hubli",
            "Ankola",
            "Bangalore",
            "Kalaseshwara Temple",
            "Agumbe",
            "Hebbe Falls",
            "India",
            "Dakshina Kannada District of Karnataka",
            "Dakshina Kannada District",
            "Karnataka",
            "Alekan Waterfalls",
            "Sita River",
            "Sahyadri Mountains"
        ],
        "http://travel.paintedstork.com/blog/2005/08/drive-in-rains-jog-falls-karwar-kali.html": [
            "Kadra",
            "Karwar",
            "Tumkur",
            "Niagara Falls",
            "Dadu",
            "Niagara",
            "Sharavati",
            "Kalinadi",
            "Bakhim",
            "Bangalore",
            "Palolem",
            "India",
            "Goa",
            "Kali",
            "Karnataka",
            "Mangalore",
            "Karawar",
            "Sagar",
            "Sharavati Valley",
            "Himalayas"
        ],
        "http://www.team-bhp.com/forum/route-travel-queries/29629-bangalore-shimogga-jog-falls-goa-mangalore-bangalore-route.html": [
            "Kalasa",
            "Bangalore",
            "India",
            "Goa",
            "Mangalore",
            "Chitradurga"
        ],
        "http://blog.sterlingholidays.com/jog-falls-karnataka-one-of-the-highest-falls-in-asia/": [
            "Arabian Sea",
            "Ankola",
            "Sharavathi",
            "Bangalore",
            "Linganamakki",
            "Thirthahalli Taluk of Shimoga",
            "India",
            "Karnataka",
            "Uttara Kannada",
            "Sagar",
            "Ambutheertha",
            "Honnavar"
        ],
        "https://www.tripadvisor.in/Attraction_Review-g1156205-d1206548-Reviews-Jog_Falls-Shimoga_Karnataka.html": [
            "Shikra",
            "Jog Falls",
            "Bangalore",
            "Mayura Gerusoppa",
            "Gokarna Beach",
            "Bhatkal"
        ],
        "http://www.indianholiday.com/tours-of-india/jog-falls-trip-bangalore.html": [
            "Mangeshi",
            "Garden City",
            "Panaji",
            "Gokarna",
            "Ankola",
            "Vagator",
            "Bangalore",
            "Panaj",
            "Ponda",
            "India",
            "Karnataka",
            "Goa",
            "Calangute Beach",
            "Anjuna Beach",
            "Mandovi",
            "Shantadurga",
            "Aguada Beach"
        ],
        "http://www.karnatakatourism.org/": [
            "Greenseer",
            "Karnataka"
        ],
        "https://www.tripoto.com/trip/bangalore-to-jog-falls-karnataka": [
            "Kolhapur",
            "Hubli",
            "Bangalore",
            "India",
            "Kempegowda Airport Bangalore",
            "Karnataka",
            "Andhra Pradesh",
            "Russia",
            "Mangalore",
            "Mumbai",
            "Kapu",
            "Maharashtra"
        ],
        "http://www.bangaloretrips.info/jogfalls": [
            "India",
            "Sharavati",
            "Lingamakki",
            "Croatia"
        ]
    }
}